LICENSE.txt
MANIFEST.in
README.rst
requirements.txt
setup.py
spectabular/__init__.py
spectabular/__main__.py
spectabular/benchmark.py
spectabular/caching.py
spectabular/dataset.py
spectabular/dataset_utils.py
spectabular/datasets.py
spectabular/delayed.py
spectabular/distributed.py
spectabular/events.py
spectabular/execution.py
spectabular/export.py
spectabular/expresso.py
spectabular/grids.py
spectabular/image.py
spectabular/kld.py
spectabular/legacy.py
spectabular/loggingconf.py
spectabular/meta.py
spectabular/misc_cmdline.py
spectabular/multithreading.py
spectabular/parallelize.py
spectabular/pca.py
spectabular/plot.py
spectabular/promise.py
spectabular/quick.py
spectabular/remote.py
spectabular/samp.py
spectabular/settings.py
spectabular/setversion.py
spectabular/transformations.py
spectabular/utils.py
spectabular/version.py
spectabular/webserver.py
spectabular/wxui.py
spectabular.egg-info/PKG-INFO
spectabular.egg-info/SOURCES.txt
spectabular.egg-info/dependency_links.txt
spectabular.egg-info/entry_points.txt
spectabular.egg-info/requires.txt
spectabular.egg-info/top_level.txt
spectabular/ext/__init__.py
spectabular/ext/bokeh.py
spectabular/ext/bqplot.py
spectabular/ext/common.py
spectabular/ext/ipyvolume.py
spectabular/ext/jprops.py
spectabular/ext/readcol.py
spectabular/file/__init__.py
spectabular/file/colfits.py
spectabular/file/gadget.py
spectabular/file/other.py
spectabular/misc/__init__.py
spectabular/misc/expressions.py
spectabular/misc/ordereddict.py
spectabular/misc/pandawrap.py
spectabular/misc/parallelize.py
spectabular/misc/progressbar.py
spectabular/misc/samp.py
spectabular/notebook/__init__.py
spectabular/notebook/bqplot.py
spectabular/notebook/ipyleaflet.py
spectabular/notebook/ipympl.py
spectabular/notebook/ipyvolume.py
spectabular/notebook/movie.py
spectabular/notebook/plot.py
spectabular/notebook/utils.py
spectabular/test/__init__.py
spectabular/test/__main__.py
spectabular/test/all.py
spectabular/test/cmodule.py
spectabular/test/dataset.py
spectabular/test/misc.py
spectabular/test/plot.py
spectabular/test/ui.py