Metadata-Version: 1.1
Name: spectabular
Version: 0.1.0
Summary: Spectabular is a graphical tool to visualize and explore large tabular datasets.
Home-page: https://www.astro.rug.nl/~breddels/spectabular
Author: Maarten A. Breddels
Author-email: maartenbreddels@gmail.com
License: MIT
Keywords: visualization exploration data analysis
Platform: UNKNOWN
Classifier: Development Status :: 4 - Beta
Classifier: License :: OSI Approved :: MIT License
Classifier: Programming Language :: Python :: 2
Classifier: Programming Language :: Python :: 2.7
Classifier: Programming Language :: Python :: 3
Classifier: Programming Language :: Python :: 3.3
Classifier: Programming Language :: Python :: 3.4
Classifier: Programming Language :: Python :: 3.5
Classifier: Operating System :: MacOS
Classifier: Operating System :: POSIX
Classifier: Operating System :: Unix
Classifier: Topic :: Scientific/Engineering :: Visualization
Classifier: Topic :: Scientific/Engineering :: Information Analysis
Classifier: Intended Audience :: Science/Research
Classifier: Environment :: MacOS X
Classifier: Environment :: X11 Applications
